xliff_mcp/__init__.py
xliff_mcp/__main__.py
xliff_mcp/auth.py
xliff_mcp/http_server.py
xliff_mcp/models.py
xliff_mcp/server.py
xliff_mcp/tmx_processor.py
xliff_mcp/xliff_processor.py
xliff_mcp_server-0.1.1.dist-info/METADATA
xliff_mcp_server-0.1.1.dist-info/WHEEL
xliff_mcp_server-0.1.1.dist-info/entry_points.txt
xliff_mcp_server-0.1.1.dist-info/licenses/LICENSE
xliff_mcp_server-0.1.1.dist-info/RECORD
