Metadata-Version: 2.4
Name: xliff-mcp-server
Version: 0.1.1
Summary: MCP server for processing XLIFF translation files
Project-URL: Homepage, https://github.com/langlink-localization/xliff-mcp-server
Project-URL: Repository, https://github.com/langlink-localization/xliff-mcp-server
Project-URL: Issues, https://github.com/langlink-localization/xliff-mcp-server/issues
Author-email: floydy <floydy@langlinking.com>
License: MIT License
License-File: LICENSE
Keywords: localization,mcp,translation,xliff
Classifier: Development Status :: 4 - Beta
Classifier: Intended Audience :: Developers
Classifier: License :: OSI Approved :: MIT License
Classifier: Programming Language :: Python :: 3
Classifier: Programming Language :: Python :: 3.10
Classifier: Programming Language :: Python :: 3.11
Classifier: Programming Language :: Python :: 3.12
Requires-Python: >=3.10
Requires-Dist: lxml>=4.9.0
Requires-Dist: mcp>=1.2.0
Requires-Dist: pydantic>=2.0.0
Requires-Dist: translate-toolkit>=3.0.0
